HW2/__init__.py
HW2/generate.py
HW2/latex.py
latex_tables_and_images-0.0.3.dist-info/METADATA
latex_tables_and_images-0.0.3.dist-info/WHEEL
latex_tables_and_images-0.0.3.dist-info/top_level.txt
latex_tables_and_images-0.0.3.dist-info/RECORD
